README.rst
genericfuncs.py
setup.py
genericfuncs.egg-info/PKG-INFO
genericfuncs.egg-info/SOURCES.txt
genericfuncs.egg-info/dependency_links.txt
genericfuncs.egg-info/top_level.txt
test/test_basic.py