Metadata-Version: 1.1
Name: genericfuncs
Version: 0.1.0
Summary: Dynamic dispatch over arbitrary predicates
Home-page: https://github.com/AvivC/genericfuncs
Author: Aviv Cohn
Author-email: avivcohn123@yahoo.com
License: MIT
Keywords: generic functions utility programming development
Platform: UNKNOWN
Classifier: Development Status :: 3 - Alpha
Classifier: Programming Language :: Python
Classifier: Programming Language :: Python :: 2
Classifier: Programming Language :: Python :: 2.7
Classifier: Intended Audience :: Developers
Classifier: License :: OSI Approved :: MIT License
Classifier: Topic :: Software Development :: Libraries
Classifier: Topic :: Software Development :: Libraries :: Python Modules
